setup.cfg
setup.py
simulacram/__init__.py
simulacram/coltypes.py
simulacram/dataset.py
simulacram/simdata.py
simulacram.egg-info/PKG-INFO
simulacram.egg-info/SOURCES.txt
simulacram.egg-info/dependency_links.txt
simulacram.egg-info/not-zip-safe
simulacram.egg-info/requires.txt
simulacram.egg-info/top_level.txt