Metadata-Version: 1.1
Name: simulacram
Version: 0.2
Summary: Create Pandas DataFrames of simulated data with columns following statistical distributions or categorical datatypes
Home-page: https://github.com/jbrambleDC/simulacram
Author: Jordan Bramble
Author-email: jordanbramble@gmail.com
License: MIT
Download-URL: https://github.com/jbrambleDC/simulacram/tarball/0.2
Keywords: simulation,data,data science
Platform: UNKNOWN
